nfasd/__init__.py
nfasd-2.0.data/scripts/nfasd
nfasd-2.0.data/scripts/register-python-argcomplete-menu
nfasd-2.0.dist-info/METADATA
nfasd-2.0.dist-info/WHEEL
nfasd-2.0.dist-info/top_level.txt
nfasd-2.0.dist-info/RECORD
