Metadata-Version: 2.1
Name: nfasd
Version: 2.0
Summary: fasd for neovim
Home-page: http://github.com/haifengkao/nfasd
Author: Hai Feng Kao
Author-email: haifeng@cocoaspice.in
License: MIT
Keywords: fasd neovim nvim nyaovim jumplist
Platform: UNKNOWN
Classifier: Development Status :: 3 - Alpha
Classifier: Environment :: Console
Classifier: Environment :: MacOS X
Classifier: Intended Audience :: Developers
Classifier: Intended Audience :: System Administrators
Classifier: Intended Audience :: End Users/Desktop
Classifier: Intended Audience :: Information Technology
Classifier: License :: OSI Approved :: MIT License
Classifier: Operating System :: MacOS
Classifier: Operating System :: Unix
Classifier: Operating System :: POSIX
Classifier: Programming Language :: Python
Classifier: Topic :: System :: Shells
Classifier: Topic :: Utilities
Requires-Dist: argcomplete
Requires-Dist: msgpack-python
